base91x/__init__.py
base91x/__main__.py
base91x/base91x.py
base91x/py.typed
base91x-1.0.1.dist-info/METADATA
base91x-1.0.1.dist-info/WHEEL
base91x-1.0.1.dist-info/entry_points.txt
base91x-1.0.1.dist-info/licenses/LICENSE
base91x-1.0.1.dist-info/RECORD
