Metadata-Version: 2.3
Name: base91x
Version: 1.0.1
Summary: base91x encoding/decoding library
Project-URL: Homepage, https://github.com/babenek/base91x
Project-URL: Bug Tracker, https://github.com/babenek/base91x/issues
Author-email: Roman Babenko <babenek@users.noreply.github.com>
License-File: LICENSE
Keywords: base91x,decode,encode
Classifier: Development Status :: 5 - Production/Stable
Classifier: Intended Audience :: Developers
Classifier: License :: OSI Approved :: MIT License
Classifier: Operating System :: OS Independent
Classifier: Programming Language :: Python :: 3
Classifier: Topic :: Software Development :: Libraries :: Python Modules
Classifier: Typing :: Typed
Requires-Python: >=3.8
